{
  "#": "from some awful first-letter birth-month type madlibs jpeg. The references to named people will not age well.",
  "@": [
    "%{badpeople} %{fouldeed} %{victims} %{vileagenda}!"
  ],
  "badpeople": [
    "AntiFa is", "Baby-eating atheists are", "Barrack Obama is",
    "Bernie Sanders is", "Black Lives Matter is", "China is", "Demons are",
    "George Soros is", "Globalists are", "Hillary Clinton is", "ISIS is",
    "Interdimensional vampires are", "Jack Dorsey is", "Mark Zuckerberg is",
    "Mexicans are", "Muslims are", "Reptilians are", "SJWs are",
    "Satanists are", "The C.I.A. is", "The Juice are", "The NSA is",
    "The elites are", "The gays are", "The lie-beral media are",
    "The new world order are"
  ],
  "fouldeed": [
    "Muslimifying", "brainwashing", "censoring", "collecting data on",
    "conspiring against", "corrupting", "experimenting upon",
    "fabricating evidence against", "hoarding wealth from",
    "interdimensionally crossbreeding with", "kidnapping", "lying about",
    "microchipping", "mind-controlling", "molesting",
    "plotting a false-flag attack against", "plotting an assassination on",
    "profiting from", "putting chemicals into", "running a psy-op on",
    "sacrificing", "spying on", "tracking",
    "unleashing Satanic powers against",
    "using concentration camps to round up", "waging war on"
  ],
  "victims": [
    "Christian children", "Donald Trump", "God-fearing Americans",
    "conservatives", "gun-owners", "members of right-wing media",
    "natural-born Americans", "straight married couples", "teenage boys",
    "the frogs", "unborn babies", "white men"
  ],
  "vileagenda": [
    "to achieve eternal life", "to control the media narrative",
    "to cover-up 9/11", "to destroy the traditional family",
    "to establish a new world order", "to overthrow the U.S. government",
    "to spread Satan-worship", "to start World War III",
    "to supress the population", "to take awy our freedoms",
    "to turn them gay"
  ]
}
